[
  {
    "label": "SGLT2i in HF (all)",
    "k": 3,
    "hr": 0.744,
    "ci_lo": 0.684,
    "ci_hi": 0.809,
    "known_hr": 0.77,
    "deviation": 3.4,
    "grade": "High",
    "verdict": "PASS",
    "time": 1.1,
    "significant": true,
    "n_searched": 83
  },
  {
    "label": "Beta-blockers in HFrEF",
    "k": 0,
    "hr": null,
    "ci_lo": null,
    "ci_hi": null,
    "known_hr": 0.66,
    "deviation": null,
    "grade": "Low",
    "verdict": "NO DATA",
    "time": 0.9,
    "significant": null,
    "n_searched": 90
  },
  {
    "label": "ACEi/ARB in HF",
    "k": 1,
    "hr": 0.8,
    "ci_lo": 0.733,
    "ci_hi": 0.873,
    "known_hr": 0.77,
    "deviation": 3.9,
    "grade": "Low",
    "verdict": "PASS",
    "time": 1.0,
    "significant": true,
    "n_searched": 82
  },
  {
    "label": "NOACs vs warfarin in AF",
    "k": 0,
    "hr": null,
    "ci_lo": null,
    "ci_hi": null,
    "known_hr": 0.81,
    "deviation": null,
    "grade": "Low",
    "verdict": "NO DATA",
    "time": 1.0,
    "significant": null,
    "n_searched": 47
  },
  {
    "label": "Statins CV prevention",
    "k": 0,
    "hr": null,
    "ci_lo": null,
    "ci_hi": null,
    "known_hr": 0.75,
    "deviation": null,
    "grade": "Low",
    "verdict": "NO DATA",
    "time": 2.2,
    "significant": null,
    "n_searched": 91
  },
  {
    "label": "PCSK9i in CVD",
    "k": 1,
    "hr": 0.85,
    "ci_lo": 0.778,
    "ci_hi": 0.928,
    "known_hr": 0.85,
    "deviation": 0.0,
    "grade": "Low",
    "verdict": "PASS",
    "time": 1.6,
    "significant": true,
    "n_searched": 85
  },
  {
    "label": "Antiplatelets in ACS",
    "k": 0,
    "hr": null,
    "ci_lo": null,
    "ci_hi": null,
    "known_hr": 0.83,
    "deviation": null,
    "grade": "Low",
    "verdict": "NO DATA",
    "time": 1.0,
    "significant": null,
    "n_searched": 69
  },
  {
    "label": "MRA in HF",
    "k": 0,
    "hr": null,
    "ci_lo": null,
    "ci_hi": null,
    "known_hr": 0.67,
    "deviation": null,
    "grade": "Low",
    "verdict": "NO DATA",
    "time": 0.9,
    "significant": null,
    "n_searched": 67
  },
  {
    "label": "GLP-1 RA CV outcomes",
    "k": 3,
    "hr": 0.837,
    "ci_lo": 0.747,
    "ci_hi": 0.938,
    "known_hr": 0.88,
    "deviation": 4.9,
    "grade": "High",
    "verdict": "PASS",
    "time": 1.0,
    "significant": true,
    "n_searched": 80
  },
  {
    "label": "ARNI vs ACEi in HF",
    "k": 0,
    "hr": null,
    "ci_lo": null,
    "ci_hi": null,
    "known_hr": 0.8,
    "deviation": null,
    "grade": "Low",
    "verdict": "NO DATA",
    "time": 0.9,
    "significant": null,
    "n_searched": 52
  }
]